UBII/TopicDataBuffer.py
UBII/TopicDataProxy.py
UBII/UbiiNetworkClient.py
UBII/__init__.py
UBII/ubii_client_node.py
UBII/ubii_service_client.py
UBII/ubii_topicdata_client.py
Ubii_Python_Node_v2-0.1.4.dist-info/LICENSE.txt
Ubii_Python_Node_v2-0.1.4.dist-info/METADATA
Ubii_Python_Node_v2-0.1.4.dist-info/WHEEL
Ubii_Python_Node_v2-0.1.4.dist-info/top_level.txt
Ubii_Python_Node_v2-0.1.4.dist-info/RECORD
