Metadata-Version: 2.1
Name: Ubii-Python-Node-v2
Version: 0.1.4
Summary: The python client node v2 for the UBII framework
Home-page: https://github.com/SandroWeber/ubii-node-python-v2
Author: Anian Kalb
Author-email: anian.games@gmx.de
Classifier: Programming Language :: Python :: 3
Requires-Python: >=3.7
License-File: LICENSE.txt
Requires-Dist: aiohttp >=3.7.4
Requires-Dist: websockets >=11.0.3
Requires-Dist: Events >=0.5
Requires-Dist: Ubii-Python-Protofiles >=0.1.1
